sfapi/__init__.py
sfapi/sfapi.py
sfapi/utils.py
sfapi-1.0.5.dist-info/METADATA
sfapi-1.0.5.dist-info/RECORD
sfapi-1.0.5.dist-info/WHEEL
sfapi-1.0.5.dist-info/top_level.txt
