Metadata-Version: 2.1
Name: sfapi
Version: 1.0.5
Summary: Simple API wrapper for Salesforce
Home-page: https://github.com/nicocrm/py-sfapi
Author: nicocrm
Author-email: nic@f1code.com
License: UNKNOWN
Platform: UNKNOWN
Classifier: Programming Language :: Python :: 3
Classifier: License :: OSI Approved :: MIT License
Classifier: Operating System :: OS Independent
Requires-Dist: requests (>=2.20.0)
